lib_telegram_scrap/__init__.py
lib_telegram_scrap/scrapper.py
lib_telegram_scrap-1.1.dist-info/METADATA
lib_telegram_scrap-1.1.dist-info/WHEEL
lib_telegram_scrap-1.1.dist-info/top_level.txt
lib_telegram_scrap-1.1.dist-info/RECORD
