Metadata-Version: 2.4
Name: lib_telegram_scrap
Version: 1.1
Summary: Library for scrap telegram chats
Home-page: https://github.com/YuranIgnatenko/lib_telegram_scrap
Author: Yurij
Author-email: yuran.ignatenko@yandex.ru
Requires-Dist: requests
Requires-Dist: beautifulsoup4
Requires-Dist: fake_useragent
Requires-Dist: telethon
Dynamic: author
Dynamic: author-email
Dynamic: description
Dynamic: description-content-type
Dynamic: home-page
Dynamic: requires-dist
Dynamic: summary
